{"nodes": [{"id": "views", "label": "views.py", "file_type": "code", "source_file": "apps\\common\\views.py", "source_location": "L1"}, {"id": "views_uploadpresignrequestserializer", "label": "UploadPresignRequestSerializer", "file_type": "code", "source_file": "apps\\common\\views.py", "source_location": "L49"}, {"id": "views_uploadpresignrequestserializer_validate", "label": ".validate()", "file_type": "code", "source_file": "apps\\common\\views.py", "source_location": "L58"}, {"id": "views_key_extension", "label": "_key_extension()", "file_type": "code", "source_file": "apps\\common\\views.py", "source_location": "L100"}, {"id": "views_sanitize_filename", "label": "_sanitize_filename()", "file_type": "code", "source_file": "apps\\common\\views.py", "source_location": "L107"}, {"id": "views_public_url_for_key", "label": "_public_url_for_key()", "file_type": "code", "source_file": "apps\\common\\views.py", "source_location": "L115"}, {"id": "views_can_edit_course", "label": "_can_edit_course()", "file_type": "code", "source_file": "apps\\common\\views.py", "source_location": "L119"}, {"id": "views_health", "label": "health()", "file_type": "code", "source_file": "apps\\common\\views.py", "source_location": "L145"}, {"id": "views_presignuploadview", "label": "PresignUploadView", "file_type": "code", "source_file": "apps\\common\\views.py", "source_location": "L182"}, {"id": "apiview", "label": "APIView", "file_type": "code", "source_file": "", "source_location": ""}, {"id": "views_presignuploadview_post", "label": ".post()", "file_type": "code", "source_file": "apps\\common\\views.py", "source_location": "L185"}, {"id": "views_storagequotaview", "label": "StorageQuotaView", "file_type": "code", "source_file": "apps\\common\\views.py", "source_location": "L322"}, {"id": "views_storagequotaview_get", "label": ".get()", "file_type": "code", "source_file": "apps\\common\\views.py", "source_location": "L325"}, {"id": "views_rationale_108", "label": "Remove path separators and other unsafe characters from filename.", "file_type": "rationale", "source_file": "apps\\common\\views.py", "source_location": "L108"}, {"id": "views_rationale_120", "label": "Same logic as CanEditCourse: admin-like can edit any; instructor only their own.", "file_type": "rationale", "source_file": "apps\\common\\views.py", "source_location": "L120"}], "edges": [{"source": "views", "target": "logging", "relation": "imports", "confidence": "EXTRACTED", "source_file": "apps\\common\\views.py", "source_location": "L1", "weight": 1.0}, {"source": "views", "target": "re", "relation": "imports", "confidence": "EXTRACTED", "source_file": "apps\\common\\views.py", "source_location": "L2", "weight": 1.0}, {"source": "views", "target": "uuid", "relation": "imports", "confidence": "EXTRACTED", "source_file": "apps\\common\\views.py", "source_location": "L3", "weight": 1.0}, {"source": "views", "target": "pathlib", "relation": "imports_from", "confidence": "EXTRACTED", "source_file": "apps\\common\\views.py", "source_location": "L4", "weight": 1.0}, {"source": "views", "target": "django_conf", "relation": "imports_from", "confidence": "EXTRACTED", "source_file": "apps\\common\\views.py", "source_location": "L8", "weight": 1.0}, {"source": "views", "target": "django_core_exceptions", "relation": "imports_from", "confidence": "EXTRACTED", "source_file": "apps\\common\\views.py", "source_location": "L9", "weight": 1.0}, {"source": "views", "target": "django_shortcuts", "relation": "imports_from", "confidence": "EXTRACTED", "source_file": "apps\\common\\views.py", "source_location": "L10", "weight": 1.0}, {"source": "views", "target": "drf_spectacular_utils", "relation": "imports_from", "confidence": "EXTRACTED", "source_file": "apps\\common\\views.py", "source_location": "L11", "weight": 1.0}, {"source": "views", "target": "rest_framework", "relation": "imports_from", "confidence": "EXTRACTED", "source_file": "apps\\common\\views.py", "source_location": "L12", "weight": 1.0}, {"source": "views", "target": "rest_framework_decorators", "relation": "imports_from", "confidence": "EXTRACTED", "source_file": "apps\\common\\views.py", "source_location": "L13", "weight": 1.0}, {"source": "views", "target": "rest_framework_permissions", "relation": "imports_from", "confidence": "EXTRACTED", "source_file": "apps\\common\\views.py", "source_location": "L14", "weight": 1.0}, {"source": "views", "target": "rest_framework_response", "relation": "imports_from", "confidence": "EXTRACTED", "source_file": "apps\\common\\views.py", "source_location": "L15", "weight": 1.0}, {"source": "views", "target": "rest_framework_views", "relation": "imports_from", "confidence": "EXTRACTED", "source_file": "apps\\common\\views.py", "source_location": "L16", "weight": 1.0}, {"source": "views", "target": "spaces", "relation": "imports_from", "confidence": "EXTRACTED", "source_file": "apps\\common\\views.py", "source_location": "L18", "weight": 1.0}, {"source": "views", "target": "apps_accounts_rbac", "relation": "imports_from", "confidence": "EXTRACTED", "source_file": "apps\\common\\views.py", "source_location": "L19", "weight": 1.0}, {"source": "views", "target": "apps_catalogue_models", "relation": "imports_from", "confidence": "EXTRACTED", "source_file": "apps\\common\\views.py", "source_location": "L20", "weight": 1.0}, {"source": "views", "target": "apps_learning_models", "relation": "imports_from", "confidence": "EXTRACTED", "source_file": "apps\\common\\views.py", "source_location": "L21", "weight": 1.0}, {"source": "views", "target": "views_uploadpresignrequestserializer", "relation": "contains", "confidence": "EXTRACTED", "source_file": "apps\\common\\views.py", "source_location": "L49", "weight": 1.0}, {"source": "views_uploadpresignrequestserializer", "target": "views_uploadpresignrequestserializer_validate", "relation": "method", "confidence": "EXTRACTED", "source_file": "apps\\common\\views.py", "source_location": "L58", "weight": 1.0}, {"source": "views", "target": "views_key_extension", "relation": "contains", "confidence": "EXTRACTED", "source_file": "apps\\common\\views.py", "source_location": "L100", "weight": 1.0}, {"source": "views", "target": "views_sanitize_filename", "relation": "contains", "confidence": "EXTRACTED", "source_file": "apps\\common\\views.py", "source_location": "L107", "weight": 1.0}, {"source": "views", "target": "views_public_url_for_key", "relation": "contains", "confidence": "EXTRACTED", "source_file": "apps\\common\\views.py", "source_location": "L115", "weight": 1.0}, {"source": "views", "target": "views_can_edit_course", "relation": "contains", "confidence": "EXTRACTED", "source_file": "apps\\common\\views.py", "source_location": "L119", "weight": 1.0}, {"source": "views", "target": "views_health", "relation": "contains", "confidence": "EXTRACTED", "source_file": "apps\\common\\views.py", "source_location": "L145", "weight": 1.0}, {"source": "views", "target": "views_presignuploadview", "relation": "contains", "confidence": "EXTRACTED", "source_file": "apps\\common\\views.py", "source_location": "L182", "weight": 1.0}, {"source": "views_presignuploadview", "target": "apiview", "relation": "inherits", "confidence": "EXTRACTED", "source_file": "apps\\common\\views.py", "source_location": "L182", "weight": 1.0}, {"source": "views_presignuploadview", "target": "views_presignuploadview_post", "relation": "method", "confidence": "EXTRACTED", "source_file": "apps\\common\\views.py", "source_location": "L185", "weight": 1.0}, {"source": "views", "target": "views_storagequotaview", "relation": "contains", "confidence": "EXTRACTED", "source_file": "apps\\common\\views.py", "source_location": "L322", "weight": 1.0}, {"source": "views_storagequotaview", "target": "apiview", "relation": "inherits", "confidence": "EXTRACTED", "source_file": "apps\\common\\views.py", "source_location": "L322", "weight": 1.0}, {"source": "views_storagequotaview", "target": "views_storagequotaview_get", "relation": "method", "confidence": "EXTRACTED", "source_file": "apps\\common\\views.py", "source_location": "L325", "weight": 1.0}, {"source": "views_uploadpresignrequestserializer_validate", "target": "views_storagequotaview_get", "relation": "calls", "confidence": "EXTRACTED", "source_file": "apps\\common\\views.py", "source_location": "L63", "weight": 1.0}, {"source": "views_key_extension", "target": "views_storagequotaview_get", "relation": "calls", "confidence": "EXTRACTED", "source_file": "apps\\common\\views.py", "source_location": "L104", "weight": 1.0}, {"source": "views_presignuploadview_post", "target": "views_uploadpresignrequestserializer", "relation": "calls", "confidence": "EXTRACTED", "source_file": "apps\\common\\views.py", "source_location": "L186", "weight": 1.0}, {"source": "views_presignuploadview_post", "target": "views_sanitize_filename", "relation": "calls", "confidence": "EXTRACTED", "source_file": "apps\\common\\views.py", "source_location": "L219", "weight": 1.0}, {"source": "views_presignuploadview_post", "target": "views_key_extension", "relation": "calls", "confidence": "EXTRACTED", "source_file": "apps\\common\\views.py", "source_location": "L220", "weight": 1.0}, {"source": "views_presignuploadview_post", "target": "views_can_edit_course", "relation": "calls", "confidence": "EXTRACTED", "source_file": "apps\\common\\views.py", "source_location": "L244", "weight": 1.0}, {"source": "views_presignuploadview_post", "target": "views_public_url_for_key", "relation": "calls", "confidence": "EXTRACTED", "source_file": "apps\\common\\views.py", "source_location": "L306", "weight": 1.0}, {"source": "views_rationale_108", "target": "views_sanitize_filename", "relation": "rationale_for", "confidence": "EXTRACTED", "source_file": "apps\\common\\views.py", "source_location": "L108", "weight": 1.0}, {"source": "views_rationale_120", "target": "views_can_edit_course", "relation": "rationale_for", "confidence": "EXTRACTED", "source_file": "apps\\common\\views.py", "source_location": "L120", "weight": 1.0}]}