{"nodes": [{"id": "views", "label": "views.py", "file_type": "code", "source_file": "apps\\learning\\views.py", "source_location": "L1"}, {"id": "views_enrollmentpagenumberpagination", "label": "EnrollmentPageNumberPagination", "file_type": "code", "source_file": "apps\\learning\\views.py", "source_location": "L28"}, {"id": "pagenumberpagination", "label": "PageNumberPagination", "file_type": "code", "source_file": "", "source_location": ""}, {"id": "views_certificatepagenumberpagination", "label": "CertificatePageNumberPagination", "file_type": "code", "source_file": "apps\\learning\\views.py", "source_location": "L33"}, {"id": "views_enrollmentviewset", "label": "EnrollmentViewSet", "file_type": "code", "source_file": "apps\\learning\\views.py", "source_location": "L59"}, {"id": "views_enrollmentviewset_get_serializer_class", "label": ".get_serializer_class()", "file_type": "code", "source_file": "apps\\learning\\views.py", "source_location": "L70"}, {"id": "views_enrollmentviewset_get_queryset", "label": ".get_queryset()", "file_type": "code", "source_file": "apps\\learning\\views.py", "source_location": "L75"}, {"id": "views_list", "label": "list()", "file_type": "code", "source_file": "apps\\learning\\views.py", "source_location": "L154"}, {"id": "views_create", "label": "create()", "file_type": "code", "source_file": "apps\\learning\\views.py", "source_location": "L167"}, {"id": "views_generate_certificate", "label": "generate_certificate()", "file_type": "code", "source_file": "apps\\learning\\views.py", "source_location": "L184"}, {"id": "views_bulk", "label": "bulk()", "file_type": "code", "source_file": "apps\\learning\\views.py", "source_location": "L219"}, {"id": "views_sessionprogressviewset", "label": "SessionProgressViewSet", "file_type": "code", "source_file": "apps\\learning\\views.py", "source_location": "L274"}, {"id": "views_sessionprogressviewset_get_serializer_class", "label": ".get_serializer_class()", "file_type": "code", "source_file": "apps\\learning\\views.py", "source_location": "L279"}, {"id": "views_sessionprogressviewset_get_queryset", "label": ".get_queryset()", "file_type": "code", "source_file": "apps\\learning\\views.py", "source_location": "L284"}, {"id": "views_sessionprogressviewset_sync_enrollment_rollup", "label": "._sync_enrollment_rollup()", "file_type": "code", "source_file": "apps\\learning\\views.py", "source_location": "L301"}, {"id": "views_sessionprogressviewset_perform_create", "label": ".perform_create()", "file_type": "code", "source_file": "apps\\learning\\views.py", "source_location": "L307"}, {"id": "views_sessionprogressviewset_perform_update", "label": ".perform_update()", "file_type": "code", "source_file": "apps\\learning\\views.py", "source_location": "L311"}, {"id": "views_update", "label": "update()", "file_type": "code", "source_file": "apps\\learning\\views.py", "source_location": "L332"}, {"id": "views_certificateviewset", "label": "CertificateViewSet", "file_type": "code", "source_file": "apps\\learning\\views.py", "source_location": "L340"}, {"id": "views_certificateviewset_get_permissions", "label": ".get_permissions()", "file_type": "code", "source_file": "apps\\learning\\views.py", "source_location": "L351"}, {"id": "views_certificateviewset_certificate_scope_queryset", "label": "._certificate_scope_queryset()", "file_type": "code", "source_file": "apps\\learning\\views.py", "source_location": "L356"}, {"id": "views_certificateviewset_get_queryset", "label": ".get_queryset()", "file_type": "code", "source_file": "apps\\learning\\views.py", "source_location": "L375"}, {"id": "views_retrieve", "label": "retrieve()", "file_type": "code", "source_file": "apps\\learning\\views.py", "source_location": "L420"}, {"id": "views_latest", "label": "latest()", "file_type": "code", "source_file": "apps\\learning\\views.py", "source_location": "L432"}, {"id": "views_verify", "label": "verify()", "file_type": "code", "source_file": "apps\\learning\\views.py", "source_location": "L451"}, {"id": "views_stats", "label": "stats()", "file_type": "code", "source_file": "apps\\learning\\views.py", "source_location": "L483"}, {"id": "views_discussionviewset", "label": "DiscussionViewSet", "file_type": "code", "source_file": "apps\\learning\\views.py", "source_location": "L513"}, {"id": "views_discussionviewset_get_serializer_class", "label": ".get_serializer_class()", "file_type": "code", "source_file": "apps\\learning\\views.py", "source_location": "L518"}, {"id": "views_discussionviewset_get_queryset", "label": ".get_queryset()", "file_type": "code", "source_file": "apps\\learning\\views.py", "source_location": "L523"}, {"id": "views_pin", "label": "pin()", "file_type": "code", "source_file": "apps\\learning\\views.py", "source_location": "L574"}, {"id": "views_lock", "label": "lock()", "file_type": "code", "source_file": "apps\\learning\\views.py", "source_location": "L592"}, {"id": "views_discussionreplyviewset", "label": "DiscussionReplyViewSet", "file_type": "code", "source_file": "apps\\learning\\views.py", "source_location": "L609"}, {"id": "views_discussionreplyviewset_get_serializer_class", "label": ".get_serializer_class()", "file_type": "code", "source_file": "apps\\learning\\views.py", "source_location": "L614"}, {"id": "views_discussionreplyviewset_get_queryset", "label": ".get_queryset()", "file_type": "code", "source_file": "apps\\learning\\views.py", "source_location": "L619"}, {"id": "views_reportviewset", "label": "ReportViewSet", "file_type": "code", "source_file": "apps\\learning\\views.py", "source_location": "L661"}, {"id": "views_reportviewset_get_serializer_class", "label": ".get_serializer_class()", "file_type": "code", "source_file": "apps\\learning\\views.py", "source_location": "L669"}, {"id": "views_reportviewset_get_queryset", "label": ".get_queryset()", "file_type": "code", "source_file": "apps\\learning\\views.py", "source_location": "L674"}, {"id": "views_types", "label": "types()", "file_type": "code", "source_file": "apps\\learning\\views.py", "source_location": "L683"}, {"id": "views_download", "label": "download()", "file_type": "code", "source_file": "apps\\learning\\views.py", "source_location": "L728"}, {"id": "views_submissionviewset", "label": "SubmissionViewSet", "file_type": "code", "source_file": "apps\\learning\\views.py", "source_location": "L777"}, {"id": "views_submissionviewset_get_serializer_class", "label": ".get_serializer_class()", "file_type": "code", "source_file": "apps\\learning\\views.py", "source_location": "L784"}, {"id": "views_submissionviewset_get_queryset", "label": ".get_queryset()", "file_type": "code", "source_file": "apps\\learning\\views.py", "source_location": "L791"}, {"id": "views_grade", "label": "grade()", "file_type": "code", "source_file": "apps\\learning\\views.py", "source_location": "L812"}, {"id": "views_statistics", "label": "statistics()", "file_type": "code", "source_file": "apps\\learning\\views.py", "source_location": "L843"}, {"id": "views_bulk_grade", "label": "bulk_grade()", "file_type": "code", "source_file": "apps\\learning\\views.py", "source_location": "L942"}, {"id": "views_quizsubmissionviewset", "label": "QuizSubmissionViewSet", "file_type": "code", "source_file": "apps\\learning\\views.py", "source_location": "L1011"}, {"id": "views_quizsubmissionviewset_get_serializer_class", "label": ".get_serializer_class()", "file_type": "code", "source_file": "apps\\learning\\views.py", "source_location": "L1021"}, {"id": "views_quizsubmissionviewset_get_queryset", "label": ".get_queryset()", "file_type": "code", "source_file": "apps\\learning\\views.py", "source_location": "L1026"}, {"id": "views_quizsubmissionviewset_create", "label": ".create()", "file_type": "code", "source_file": "apps\\learning\\views.py", "source_location": "L1054"}, {"id": "views_learninganalyticsviewset", "label": "LearningAnalyticsViewSet", "file_type": "code", "source_file": "apps\\learning\\views.py", "source_location": "L1068"}, {"id": "views_enrollment_trends", "label": "enrollment_trends()", "file_type": "code", "source_file": "apps\\learning\\views.py", "source_location": "L1073"}, {"id": "views_learning_stats", "label": "learning_stats()", "file_type": "code", "source_file": "apps\\learning\\views.py", "source_location": "L1126"}, {"id": "views_top_course_performance", "label": "top_course_performance()", "file_type": "code", "source_file": "apps\\learning\\views.py", "source_location": "L1159"}, {"id": "views_badgeviewset", "label": "BadgeViewSet", "file_type": "code", "source_file": "apps\\learning\\views.py", "source_location": "L1213"}, {"id": "views_badgeviewset_get_serializer_class", "label": ".get_serializer_class()", "file_type": "code", "source_file": "apps\\learning\\views.py", "source_location": "L1222"}, {"id": "views_badgeviewset_get_queryset", "label": ".get_queryset()", "file_type": "code", "source_file": "apps\\learning\\views.py", "source_location": "L1228"}, {"id": "views_my_badges", "label": "my_badges()", "file_type": "code", "source_file": "apps\\learning\\views.py", "source_location": "L1244"}, {"id": "views_check_badges", "label": "check_badges()", "file_type": "code", "source_file": "apps\\learning\\views.py", "source_location": "L1256"}, {"id": "views_savedcourseviewset", "label": "SavedCourseViewSet", "file_type": "code", "source_file": "apps\\learning\\views.py", "source_location": "L1272"}, {"id": "views_savedcourseviewset_get_queryset", "label": ".get_queryset()", "file_type": "code", "source_file": "apps\\learning\\views.py", "source_location": "L1283"}, {"id": "views_savedcourseviewset_perform_create", "label": ".perform_create()", "file_type": "code", "source_file": "apps\\learning\\views.py", "source_location": "L1288"}, {"id": "views_destroy", "label": "destroy()", "file_type": "code", "source_file": "apps\\learning\\views.py", "source_location": "L1310"}, {"id": "views_toggle", "label": "toggle()", "file_type": "code", "source_file": "apps\\learning\\views.py", "source_location": "L1320"}, {"id": "views_workshopviewset", "label": "WorkshopViewSet", "file_type": "code", "source_file": "apps\\learning\\views.py", "source_location": "L1352"}, {"id": "views_workshopviewset_get_serializer_class", "label": ".get_serializer_class()", "file_type": "code", "source_file": "apps\\learning\\views.py", "source_location": "L1361"}, {"id": "views_workshopviewset_get_queryset", "label": ".get_queryset()", "file_type": "code", "source_file": "apps\\learning\\views.py", "source_location": "L1366"}, {"id": "views_workshopviewset_perform_create", "label": ".perform_create()", "file_type": "code", "source_file": "apps\\learning\\views.py", "source_location": "L1390"}, {"id": "views_partial_update", "label": "partial_update()", "file_type": "code", "source_file": "apps\\learning\\views.py", "source_location": "L1417"}, {"id": "views_rationale_65", "label": "ViewSet for managing user enrollments. Supports list, create, retrieve, and gene", "file_type": "rationale", "source_file": "apps\\learning\\views.py", "source_location": "L65"}, {"id": "views_rationale_275", "label": "ViewSet for managing session progress.", "file_type": "rationale", "source_file": "apps\\learning\\views.py", "source_location": "L275"}, {"id": "views_rationale_302", "label": "Keep enrollment progress and resume fields aligned after SessionProgress writes.", "file_type": "rationale", "source_file": "apps\\learning\\views.py", "source_location": "L302"}, {"id": "views_rationale_341", "label": "ViewSet for managing certificates.", "file_type": "rationale", "source_file": "apps\\learning\\views.py", "source_location": "L341"}, {"id": "views_rationale_357", "label": "Role-scoped base queryset (no list search/course filters). Used for list/retriev", "file_type": "rationale", "source_file": "apps\\learning\\views.py", "source_location": "L357"}, {"id": "views_rationale_484", "label": "Certificate statistics over the same role scope as list (no search/course filter", "file_type": "rationale", "source_file": "apps\\learning\\views.py", "source_location": "L484"}, {"id": "views_rationale_514", "label": "ViewSet for managing discussions.", "file_type": "rationale", "source_file": "apps\\learning\\views.py", "source_location": "L514"}, {"id": "views_rationale_575", "label": "Pin or unpin a discussion thread.", "file_type": "rationale", "source_file": "apps\\learning\\views.py", "source_location": "L575"}, {"id": "views_rationale_593", "label": "Lock or unlock a discussion thread.", "file_type": "rationale", "source_file": "apps\\learning\\views.py", "source_location": "L593"}, {"id": "views_rationale_610", "label": "ViewSet for managing discussion replies.", "file_type": "rationale", "source_file": "apps\\learning\\views.py", "source_location": "L610"}, {"id": "views_rationale_662", "label": "ViewSet for managing organization reports.     Supports listing reports, genera", "file_type": "rationale", "source_file": "apps\\learning\\views.py", "source_location": "L662"}, {"id": "views_rationale_684", "label": "Get available report types", "file_type": "rationale", "source_file": "apps\\learning\\views.py", "source_location": "L684"}, {"id": "views_rationale_700", "label": "Generate a new report", "file_type": "rationale", "source_file": "apps\\learning\\views.py", "source_location": "L700"}, {"id": "views_rationale_778", "label": "ViewSet for managing learner submissions and grades.", "file_type": "rationale", "source_file": "apps\\learning\\views.py", "source_location": "L778"}, {"id": "views_rationale_813", "label": "Grade a submission (instructor/admin only)", "file_type": "rationale", "source_file": "apps\\learning\\views.py", "source_location": "L813"}, {"id": "views_rationale_844", "label": "Get grade distribution for a course", "file_type": "rationale", "source_file": "apps\\learning\\views.py", "source_location": "L844"}, {"id": "views_rationale_899", "label": "Admin-level assessment statistics.", "file_type": "rationale", "source_file": "apps\\learning\\views.py", "source_location": "L899"}, {"id": "views_rationale_943", "label": "Bulk grade submissions (instructor/admin only)", "file_type": "rationale", "source_file": "apps\\learning\\views.py", "source_location": "L943"}, {"id": "views_rationale_1012", "label": "ViewSet for quiz submissions.     - POST: Submit quiz answers (auto-grades)", "file_type": "rationale", "source_file": "apps\\learning\\views.py", "source_location": "L1012"}, {"id": "views_rationale_1069", "label": "ViewSet for dashboard analytics regarding enrollments and completion.", "file_type": "rationale", "source_file": "apps\\learning\\views.py", "source_location": "L1069"}, {"id": "views_rationale_1160", "label": "Per-course enrollment and completion aggregates for analytics dashboards.", "file_type": "rationale", "source_file": "apps\\learning\\views.py", "source_location": "L1160"}, {"id": "views_rationale_1214", "label": "ViewSet for badges.     - GET  /badges/         \u2192 list all badge definitions", "file_type": "rationale", "source_file": "apps\\learning\\views.py", "source_location": "L1214"}, {"id": "views_rationale_1279", "label": "ViewSet for managing saved/bookmarked courses.", "file_type": "rationale", "source_file": "apps\\learning\\views.py", "source_location": "L1279"}, {"id": "views_rationale_1353", "label": "CRUD for Workshops (in-person training events).     - Instructors see only thei", "file_type": "rationale", "source_file": "apps\\learning\\views.py", "source_location": "L1353"}], "edges": [{"source": "views", "target": "django_contrib_auth", "relation": "imports_from", "confidence": "EXTRACTED", "source_file": "apps\\learning\\views.py", "source_location": "L1", "weight": 1.0}, {"source": "views", "target": "django_db_models", "relation": "imports_from", "confidence": "EXTRACTED", "source_file": "apps\\learning\\views.py", "source_location": "L2", "weight": 1.0}, {"source": "views", "target": "django_utils", "relation": "imports_from", "confidence": "EXTRACTED", "source_file": "apps\\learning\\views.py", "source_location": "L3", "weight": 1.0}, {"source": "views", "target": "drf_spectacular_utils", "relation": "imports_from", "confidence": "EXTRACTED", "source_file": "apps\\learning\\views.py", "source_location": "L4", "weight": 1.0}, {"source": "views", "target": "rest_framework", "relation": "imports_from", "confidence": "EXTRACTED", "source_file": "apps\\learning\\views.py", "source_location": "L5", "weight": 1.0}, {"source": "views", "target": "rest_framework_decorators", "relation": "imports_from", "confidence": "EXTRACTED", "source_file": "apps\\learning\\views.py", "source_location": "L6", "weight": 1.0}, {"source": "views", "target": "rest_framework_pagination", "relation": "imports_from", "confidence": "EXTRACTED", "source_file": "apps\\learning\\views.py", "source_location": "L7", "weight": 1.0}, {"source": "views", "target": "rest_framework_permissions", "relation": "imports_from", "confidence": "EXTRACTED", "source_file": "apps\\learning\\views.py", "source_location": "L8", "weight": 1.0}, {"source": "views", "target": "rest_framework_response", "relation": "imports_from", "confidence": "EXTRACTED", "source_file": "apps\\learning\\views.py", "source_location": "L9", "weight": 1.0}, {"source": "views", "target": "apps_payments_permissions", "relation": "imports_from", "confidence": "EXTRACTED", "source_file": "apps\\learning\\views.py", "source_location": "L11", "weight": 1.0}, {"source": "views", "target": "apps_accounts_rbac", "relation": "imports_from", "confidence": "EXTRACTED", "source_file": "apps\\learning\\views.py", "source_location": "L12", "weight": 1.0}, {"source": "views", "target": "views_enrollmentpagenumberpagination", "relation": "contains", "confidence": "EXTRACTED", "source_file": "apps\\learning\\views.py", "source_location": "L28", "weight": 1.0}, {"source": "views_enrollmentpagenumberpagination", "target": "pagenumberpagination", "relation": "inherits", "confidence": "EXTRACTED", "source_file": "apps\\learning\\views.py", "source_location": "L28", "weight": 1.0}, {"source": "views", "target": "views_certificatepagenumberpagination", "relation": "contains", "confidence": "EXTRACTED", "source_file": "apps\\learning\\views.py", "source_location": "L33", "weight": 1.0}, {"source": "views_certificatepagenumberpagination", "target": "pagenumberpagination", "relation": "inherits", "confidence": "EXTRACTED", "source_file": "apps\\learning\\views.py", "source_location": "L33", "weight": 1.0}, {"source": "views", "target": "models", "relation": "imports_from", "confidence": "EXTRACTED", "source_file": "apps\\learning\\views.py", "source_location": "L37", "weight": 1.0}, {"source": "views", "target": "serializers", "relation": "imports_from", "confidence": "EXTRACTED", "source_file": "apps\\learning\\views.py", "source_location": "L41", "weight": 1.0}, {"source": "views", "target": "views_enrollmentviewset", "relation": "contains", "confidence": "EXTRACTED", "source_file": "apps\\learning\\views.py", "source_location": "L59", "weight": 1.0}, {"source": "views_enrollmentviewset", "target": "views_enrollmentviewset_get_serializer_class", "relation": "method", "confidence": "EXTRACTED", "source_file": "apps\\learning\\views.py", "source_location": "L70", "weight": 1.0}, {"source": "views_enrollmentviewset", "target": "views_enrollmentviewset_get_queryset", "relation": "method", "confidence": "EXTRACTED", "source_file": "apps\\learning\\views.py", "source_location": "L75", "weight": 1.0}, {"source": "views", "target": "views_list", "relation": "contains", "confidence": "EXTRACTED", "source_file": "apps\\learning\\views.py", "source_location": "L154", "weight": 1.0}, {"source": "views", "target": "views_create", "relation": "contains", "confidence": "EXTRACTED", "source_file": "apps\\learning\\views.py", "source_location": "L167", "weight": 1.0}, {"source": "views", "target": "views_generate_certificate", "relation": "contains", "confidence": "EXTRACTED", "source_file": "apps\\learning\\views.py", "source_location": "L184", "weight": 1.0}, {"source": "views", "target": "views_bulk", "relation": "contains", "confidence": "EXTRACTED", "source_file": "apps\\learning\\views.py", "source_location": "L219", "weight": 1.0}, {"source": "views", "target": "views_sessionprogressviewset", "relation": "contains", "confidence": "EXTRACTED", "source_file": "apps\\learning\\views.py", "source_location": "L274", "weight": 1.0}, {"source": "views_sessionprogressviewset", "target": "views_sessionprogressviewset_get_serializer_class", "relation": "method", "confidence": "EXTRACTED", "source_file": "apps\\learning\\views.py", "source_location": "L279", "weight": 1.0}, {"source": "views_sessionprogressviewset", "target": "views_sessionprogressviewset_get_queryset", "relation": "method", "confidence": "EXTRACTED", "source_file": "apps\\learning\\views.py", "source_location": "L284", "weight": 1.0}, {"source": "views_sessionprogressviewset", "target": "views_sessionprogressviewset_sync_enrollment_rollup", "relation": "method", "confidence": "EXTRACTED", "source_file": "apps\\learning\\views.py", "source_location": "L301", "weight": 1.0}, {"source": "views_sessionprogressviewset", "target": "views_sessionprogressviewset_perform_create", "relation": "method", "confidence": "EXTRACTED", "source_file": "apps\\learning\\views.py", "source_location": "L307", "weight": 1.0}, {"source": "views_sessionprogressviewset", "target": "views_sessionprogressviewset_perform_update", "relation": "method", "confidence": "EXTRACTED", "source_file": "apps\\learning\\views.py", "source_location": "L311", "weight": 1.0}, {"source": "views", "target": "views_list", "relation": "contains", "confidence": "EXTRACTED", "source_file": "apps\\learning\\views.py", "source_location": "L324", "weight": 1.0}, {"source": "views", "target": "views_update", "relation": "contains", "confidence": "EXTRACTED", "source_file": "apps\\learning\\views.py", "source_location": "L332", "weight": 1.0}, {"source": "views", "target": "views_certificateviewset", "relation": "contains", "confidence": "EXTRACTED", "source_file": "apps\\learning\\views.py", "source_location": "L340", "weight": 1.0}, {"source": "views_certificateviewset", "target": "views_certificateviewset_get_permissions", "relation": "method", "confidence": "EXTRACTED", "source_file": "apps\\learning\\views.py", "source_location": "L351", "weight": 1.0}, {"source": "views_certificateviewset", "target": "views_certificateviewset_certificate_scope_queryset", "relation": "method", "confidence": "EXTRACTED", "source_file": "apps\\learning\\views.py", "source_location": "L356", "weight": 1.0}, {"source": "views_certificateviewset", "target": "views_certificateviewset_get_queryset", "relation": "method", "confidence": "EXTRACTED", "source_file": "apps\\learning\\views.py", "source_location": "L375", "weight": 1.0}, {"source": "views", "target": "views_list", "relation": "contains", "confidence": "EXTRACTED", "source_file": "apps\\learning\\views.py", "source_location": "L413", "weight": 1.0}, {"source": "views", "target": "views_retrieve", "relation": "contains", "confidence": "EXTRACTED", "source_file": "apps\\learning\\views.py", "source_location": "L420", "weight": 1.0}, {"source": "views", "target": "views_latest", "relation": "contains", "confidence": "EXTRACTED", "source_file": "apps\\learning\\views.py", "source_location": "L432", "weight": 1.0}, {"source": "views", "target": "views_verify", "relation": "contains", "confidence": "EXTRACTED", "source_file": "apps\\learning\\views.py", "source_location": "L451", "weight": 1.0}, {"source": "views", "target": "views_stats", "relation": "contains", "confidence": "EXTRACTED", "source_file": "apps\\learning\\views.py", "source_location": "L483", "weight": 1.0}, {"source": "views", "target": "views_discussionviewset", "relation": "contains", "confidence": "EXTRACTED", "source_file": "apps\\learning\\views.py", "source_location": "L513", "weight": 1.0}, {"source": "views_discussionviewset", "target": "views_discussionviewset_get_serializer_class", "relation": "method", "confidence": "EXTRACTED", "source_file": "apps\\learning\\views.py", "source_location": "L518", "weight": 1.0}, {"source": "views_discussionviewset", "target": "views_discussionviewset_get_queryset", "relation": "method", "confidence": "EXTRACTED", "source_file": "apps\\learning\\views.py", "source_location": "L523", "weight": 1.0}, {"source": "views", "target": "views_list", "relation": "contains", "confidence": "EXTRACTED", "source_file": "apps\\learning\\views.py", "source_location": "L550", "weight": 1.0}, {"source": "views", "target": "views_create", "relation": "contains", "confidence": "EXTRACTED", "source_file": "apps\\learning\\views.py", "source_location": "L558", "weight": 1.0}, {"source": "views", "target": "views_retrieve", "relation": "contains", "confidence": "EXTRACTED", "source_file": "apps\\learning\\views.py", "source_location": "L565", "weight": 1.0}, {"source": "views", "target": "views_pin", "relation": "contains", "confidence": "EXTRACTED", "source_file": "apps\\learning\\views.py", "source_location": "L574", "weight": 1.0}, {"source": "views", "target": "views_lock", "relation": "contains", "confidence": "EXTRACTED", "source_file": "apps\\learning\\views.py", "source_location": "L592", "weight": 1.0}, {"source": "views", "target": "views_discussionreplyviewset", "relation": "contains", "confidence": "EXTRACTED", "source_file": "apps\\learning\\views.py", "source_location": "L609", "weight": 1.0}, {"source": "views_discussionreplyviewset", "target": "views_discussionreplyviewset_get_serializer_class", "relation": "method", "confidence": "EXTRACTED", "source_file": "apps\\learning\\views.py", "source_location": "L614", "weight": 1.0}, {"source": "views_discussionreplyviewset", "target": "views_discussionreplyviewset_get_queryset", "relation": "method", "confidence": "EXTRACTED", "source_file": "apps\\learning\\views.py", "source_location": "L619", "weight": 1.0}, {"source": "views", "target": "views_list", "relation": "contains", "confidence": "EXTRACTED", "source_file": "apps\\learning\\views.py", "source_location": "L629", "weight": 1.0}, {"source": "views", "target": "views_create", "relation": "contains", "confidence": "EXTRACTED", "source_file": "apps\\learning\\views.py", "source_location": "L637", "weight": 1.0}, {"source": "views", "target": "views_reportviewset", "relation": "contains", "confidence": "EXTRACTED", "source_file": "apps\\learning\\views.py", "source_location": "L661", "weight": 1.0}, {"source": "views_reportviewset", "target": "views_reportviewset_get_serializer_class", "relation": "method", "confidence": "EXTRACTED", "source_file": "apps\\learning\\views.py", "source_location": "L669", "weight": 1.0}, {"source": "views_reportviewset", "target": "views_reportviewset_get_queryset", "relation": "method", "confidence": "EXTRACTED", "source_file": "apps\\learning\\views.py", "source_location": "L674", "weight": 1.0}, {"source": "views", "target": "views_types", "relation": "contains", "confidence": "EXTRACTED", "source_file": "apps\\learning\\views.py", "source_location": "L683", "weight": 1.0}, {"source": "views", "target": "views_create", "relation": "contains", "confidence": "EXTRACTED", "source_file": "apps\\learning\\views.py", "source_location": "L699", "weight": 1.0}, {"source": "views", "target": "views_download", "relation": "contains", "confidence": "EXTRACTED", "source_file": "apps\\learning\\views.py", "source_location": "L728", "weight": 1.0}, {"source": "views", "target": "views_submissionviewset", "relation": "contains", "confidence": "EXTRACTED", "source_file": "apps\\learning\\views.py", "source_location": "L777", "weight": 1.0}, {"source": "views_submissionviewset", "target": "views_submissionviewset_get_serializer_class", "relation": "method", "confidence": "EXTRACTED", "source_file": "apps\\learning\\views.py", "source_location": "L784", "weight": 1.0}, {"source": "views_submissionviewset", "target": "views_submissionviewset_get_queryset", "relation": "method", "confidence": "EXTRACTED", "source_file": "apps\\learning\\views.py", "source_location": "L791", "weight": 1.0}, {"source": "views", "target": "views_grade", "relation": "contains", "confidence": "EXTRACTED", "source_file": "apps\\learning\\views.py", "source_location": "L812", "weight": 1.0}, {"source": "views", "target": "views_statistics", "relation": "contains", "confidence": "EXTRACTED", "source_file": "apps\\learning\\views.py", "source_location": "L843", "weight": 1.0}, {"source": "views", "target": "views_stats", "relation": "contains", "confidence": "EXTRACTED", "source_file": "apps\\learning\\views.py", "source_location": "L898", "weight": 1.0}, {"source": "views", "target": "views_bulk_grade", "relation": "contains", "confidence": "EXTRACTED", "source_file": "apps\\learning\\views.py", "source_location": "L942", "weight": 1.0}, {"source": "views", "target": "views_quizsubmissionviewset", "relation": "contains", "confidence": "EXTRACTED", "source_file": "apps\\learning\\views.py", "source_location": "L1011", "weight": 1.0}, {"source": "views_quizsubmissionviewset", "target": "views_quizsubmissionviewset_get_serializer_class", "relation": "method", "confidence": "EXTRACTED", "source_file": "apps\\learning\\views.py", "source_location": "L1021", "weight": 1.0}, {"source": "views_quizsubmissionviewset", "target": "views_quizsubmissionviewset_get_queryset", "relation": "method", "confidence": "EXTRACTED", "source_file": "apps\\learning\\views.py", "source_location": "L1026", "weight": 1.0}, {"source": "views_quizsubmissionviewset", "target": "views_quizsubmissionviewset_create", "relation": "method", "confidence": "EXTRACTED", "source_file": "apps\\learning\\views.py", "source_location": "L1054", "weight": 1.0}, {"source": "views", "target": "django_db_models", "relation": "imports_from", "confidence": "EXTRACTED", "source_file": "apps\\learning\\views.py", "source_location": "L1063", "weight": 1.0}, {"source": "views", "target": "django_db_models_functions", "relation": "imports_from", "confidence": "EXTRACTED", "source_file": "apps\\learning\\views.py", "source_location": "L1064", "weight": 1.0}, {"source": "views", "target": "datetime", "relation": "imports_from", "confidence": "EXTRACTED", "source_file": "apps\\learning\\views.py", "source_location": "L1065", "weight": 1.0}, {"source": "views", "target": "views_learninganalyticsviewset", "relation": "contains", "confidence": "EXTRACTED", "source_file": "apps\\learning\\views.py", "source_location": "L1068", "weight": 1.0}, {"source": "views", "target": "views_enrollment_trends", "relation": "contains", "confidence": "EXTRACTED", "source_file": "apps\\learning\\views.py", "source_location": "L1073", "weight": 1.0}, {"source": "views", "target": "views_learning_stats", "relation": "contains", "confidence": "EXTRACTED", "source_file": "apps\\learning\\views.py", "source_location": "L1126", "weight": 1.0}, {"source": "views", "target": "views_top_course_performance", "relation": "contains", "confidence": "EXTRACTED", "source_file": "apps\\learning\\views.py", "source_location": "L1159", "weight": 1.0}, {"source": "views", "target": "views_badgeviewset", "relation": "contains", "confidence": "EXTRACTED", "source_file": "apps\\learning\\views.py", "source_location": "L1213", "weight": 1.0}, {"source": "views_badgeviewset", "target": "views_badgeviewset_get_serializer_class", "relation": "method", "confidence": "EXTRACTED", "source_file": "apps\\learning\\views.py", "source_location": "L1222", "weight": 1.0}, {"source": "views_badgeviewset", "target": "views_badgeviewset_get_queryset", "relation": "method", "confidence": "EXTRACTED", "source_file": "apps\\learning\\views.py", "source_location": "L1228", "weight": 1.0}, {"source": "views", "target": "views_list", "relation": "contains", "confidence": "EXTRACTED", "source_file": "apps\\learning\\views.py", "source_location": "L1236", "weight": 1.0}, {"source": "views", "target": "views_my_badges", "relation": "contains", "confidence": "EXTRACTED", "source_file": "apps\\learning\\views.py", "source_location": "L1244", "weight": 1.0}, {"source": "views", "target": "views_check_badges", "relation": "contains", "confidence": "EXTRACTED", "source_file": "apps\\learning\\views.py", "source_location": "L1256", "weight": 1.0}, {"source": "views", "target": "views_savedcourseviewset", "relation": "contains", "confidence": "EXTRACTED", "source_file": "apps\\learning\\views.py", "source_location": "L1272", "weight": 1.0}, {"source": "views_savedcourseviewset", "target": "views_savedcourseviewset_get_queryset", "relation": "method", "confidence": "EXTRACTED", "source_file": "apps\\learning\\views.py", "source_location": "L1283", "weight": 1.0}, {"source": "views_savedcourseviewset", "target": "views_savedcourseviewset_perform_create", "relation": "method", "confidence": "EXTRACTED", "source_file": "apps\\learning\\views.py", "source_location": "L1288", "weight": 1.0}, {"source": "views", "target": "views_list", "relation": "contains", "confidence": "EXTRACTED", "source_file": "apps\\learning\\views.py", "source_location": "L1295", "weight": 1.0}, {"source": "views", "target": "views_create", "relation": "contains", "confidence": "EXTRACTED", "source_file": "apps\\learning\\views.py", "source_location": "L1303", "weight": 1.0}, {"source": "views", "target": "views_destroy", "relation": "contains", "confidence": "EXTRACTED", "source_file": "apps\\learning\\views.py", "source_location": "L1310", "weight": 1.0}, {"source": "views", "target": "views_toggle", "relation": "contains", "confidence": "EXTRACTED", "source_file": "apps\\learning\\views.py", "source_location": "L1320", "weight": 1.0}, {"source": "views", "target": "views_workshopviewset", "relation": "contains", "confidence": "EXTRACTED", "source_file": "apps\\learning\\views.py", "source_location": "L1352", "weight": 1.0}, {"source": "views_workshopviewset", "target": "views_workshopviewset_get_serializer_class", "relation": "method", "confidence": "EXTRACTED", "source_file": "apps\\learning\\views.py", "source_location": "L1361", "weight": 1.0}, {"source": "views_workshopviewset", "target": "views_workshopviewset_get_queryset", "relation": "method", "confidence": "EXTRACTED", "source_file": "apps\\learning\\views.py", "source_location": "L1366", "weight": 1.0}, {"source": "views_workshopviewset", "target": "views_workshopviewset_perform_create", "relation": "method", "confidence": "EXTRACTED", "source_file": "apps\\learning\\views.py", "source_location": "L1390", "weight": 1.0}, {"source": "views", "target": "views_list", "relation": "contains", "confidence": "EXTRACTED", "source_file": "apps\\learning\\views.py", "source_location": "L1401", "weight": 1.0}, {"source": "views", "target": "views_create", "relation": "contains", "confidence": "EXTRACTED", "source_file": "apps\\learning\\views.py", "source_location": "L1405", "weight": 1.0}, {"source": "views", "target": "views_retrieve", "relation": "contains", "confidence": "EXTRACTED", "source_file": "apps\\learning\\views.py", "source_location": "L1409", "weight": 1.0}, {"source": "views", "target": "views_update", "relation": "contains", "confidence": "EXTRACTED", "source_file": "apps\\learning\\views.py", "source_location": "L1413", "weight": 1.0}, {"source": "views", "target": "views_partial_update", "relation": "contains", "confidence": "EXTRACTED", "source_file": "apps\\learning\\views.py", "source_location": "L1417", "weight": 1.0}, {"source": "views", "target": "views_destroy", "relation": "contains", "confidence": "EXTRACTED", "source_file": "apps\\learning\\views.py", "source_location": "L1421", "weight": 1.0}, {"source": "views_sessionprogressviewset_perform_create", "target": "views_sessionprogressviewset_sync_enrollment_rollup", "relation": "calls", "confidence": "EXTRACTED", "source_file": "apps\\learning\\views.py", "source_location": "L309", "weight": 1.0}, {"source": "views_sessionprogressviewset_perform_update", "target": "views_sessionprogressviewset_sync_enrollment_rollup", "relation": "calls", "confidence": "EXTRACTED", "source_file": "apps\\learning\\views.py", "source_location": "L313", "weight": 1.0}, {"source": "views_certificateviewset_get_queryset", "target": "views_certificateviewset_certificate_scope_queryset", "relation": "calls", "confidence": "EXTRACTED", "source_file": "apps\\learning\\views.py", "source_location": "L376", "weight": 1.0}, {"source": "views_latest", "target": "views_workshopviewset_get_queryset", "relation": "calls", "confidence": "EXTRACTED", "source_file": "apps\\learning\\views.py", "source_location": "L433", "weight": 1.0}, {"source": "views_stats", "target": "views_certificateviewset_certificate_scope_queryset", "relation": "calls", "confidence": "EXTRACTED", "source_file": "apps\\learning\\views.py", "source_location": "L492", "weight": 1.0}, {"source": "views_create", "target": "views_quizsubmissionviewset_create", "relation": "calls", "confidence": "EXTRACTED", "source_file": "apps\\learning\\views.py", "source_location": "L559", "weight": 1.0}, {"source": "views_enrollment_trends", "target": "views_list", "relation": "calls", "confidence": "EXTRACTED", "source_file": "apps\\learning\\views.py", "source_location": "L1115", "weight": 1.0}, {"source": "views_toggle", "target": "views_quizsubmissionviewset_create", "relation": "calls", "confidence": "EXTRACTED", "source_file": "apps\\learning\\views.py", "source_location": "L1341", "weight": 1.0}, {"source": "views_rationale_65", "target": "views_enrollmentviewset", "relation": "rationale_for", "confidence": "EXTRACTED", "source_file": "apps\\learning\\views.py", "source_location": "L65", "weight": 1.0}, {"source": "views_rationale_275", "target": "views_sessionprogressviewset", "relation": "rationale_for", "confidence": "EXTRACTED", "source_file": "apps\\learning\\views.py", "source_location": "L275", "weight": 1.0}, {"source": "views_rationale_302", "target": "views_sessionprogressviewset_sync_enrollment_rollup", "relation": "rationale_for", "confidence": "EXTRACTED", "source_file": "apps\\learning\\views.py", "source_location": "L302", "weight": 1.0}, {"source": "views_rationale_341", "target": "views_certificateviewset", "relation": "rationale_for", "confidence": "EXTRACTED", "source_file": "apps\\learning\\views.py", "source_location": "L341", "weight": 1.0}, {"source": "views_rationale_357", "target": "views_certificateviewset_certificate_scope_queryset", "relation": "rationale_for", "confidence": "EXTRACTED", "source_file": "apps\\learning\\views.py", "source_location": "L357", "weight": 1.0}, {"source": "views_rationale_484", "target": "views_certificateviewset_stats", "relation": "rationale_for", "confidence": "EXTRACTED", "source_file": "apps\\learning\\views.py", "source_location": "L484", "weight": 1.0}, {"source": "views_rationale_514", "target": "views_discussionviewset", "relation": "rationale_for", "confidence": "EXTRACTED", "source_file": "apps\\learning\\views.py", "source_location": "L514", "weight": 1.0}, {"source": "views_rationale_575", "target": "views_discussionviewset_pin", "relation": "rationale_for", "confidence": "EXTRACTED", "source_file": "apps\\learning\\views.py", "source_location": "L575", "weight": 1.0}, {"source": "views_rationale_593", "target": "views_discussionviewset_lock", "relation": "rationale_for", "confidence": "EXTRACTED", "source_file": "apps\\learning\\views.py", "source_location": "L593", "weight": 1.0}, {"source": "views_rationale_610", "target": "views_discussionreplyviewset", "relation": "rationale_for", "confidence": "EXTRACTED", "source_file": "apps\\learning\\views.py", "source_location": "L610", "weight": 1.0}, {"source": "views_rationale_662", "target": "views_reportviewset", "relation": "rationale_for", "confidence": "EXTRACTED", "source_file": "apps\\learning\\views.py", "source_location": "L662", "weight": 1.0}, {"source": "views_rationale_684", "target": "views_reportviewset_types", "relation": "rationale_for", "confidence": "EXTRACTED", "source_file": "apps\\learning\\views.py", "source_location": "L684", "weight": 1.0}, {"source": "views_rationale_700", "target": "views_reportviewset_create", "relation": "rationale_for", "confidence": "EXTRACTED", "source_file": "apps\\learning\\views.py", "source_location": "L700", "weight": 1.0}, {"source": "views_rationale_778", "target": "views_submissionviewset", "relation": "rationale_for", "confidence": "EXTRACTED", "source_file": "apps\\learning\\views.py", "source_location": "L778", "weight": 1.0}, {"source": "views_rationale_813", "target": "views_submissionviewset_grade", "relation": "rationale_for", "confidence": "EXTRACTED", "source_file": "apps\\learning\\views.py", "source_location": "L813", "weight": 1.0}, {"source": "views_rationale_844", "target": "views_submissionviewset_statistics", "relation": "rationale_for", "confidence": "EXTRACTED", "source_file": "apps\\learning\\views.py", "source_location": "L844", "weight": 1.0}, {"source": "views_rationale_899", "target": "views_submissionviewset_stats", "relation": "rationale_for", "confidence": "EXTRACTED", "source_file": "apps\\learning\\views.py", "source_location": "L899", "weight": 1.0}, {"source": "views_rationale_943", "target": "views_submissionviewset_bulk_grade", "relation": "rationale_for", "confidence": "EXTRACTED", "source_file": "apps\\learning\\views.py", "source_location": "L943", "weight": 1.0}, {"source": "views_rationale_1012", "target": "views_quizsubmissionviewset", "relation": "rationale_for", "confidence": "EXTRACTED", "source_file": "apps\\learning\\views.py", "source_location": "L1012", "weight": 1.0}, {"source": "views_rationale_1069", "target": "views_learninganalyticsviewset", "relation": "rationale_for", "confidence": "EXTRACTED", "source_file": "apps\\learning\\views.py", "source_location": "L1069", "weight": 1.0}, {"source": "views_rationale_1160", "target": "views_learninganalyticsviewset_top_course_performance", "relation": "rationale_for", "confidence": "EXTRACTED", "source_file": "apps\\learning\\views.py", "source_location": "L1160", "weight": 1.0}, {"source": "views_rationale_1214", "target": "views_badgeviewset", "relation": "rationale_for", "confidence": "EXTRACTED", "source_file": "apps\\learning\\views.py", "source_location": "L1214", "weight": 1.0}, {"source": "views_rationale_1279", "target": "views_savedcourseviewset", "relation": "rationale_for", "confidence": "EXTRACTED", "source_file": "apps\\learning\\views.py", "source_location": "L1279", "weight": 1.0}, {"source": "views_rationale_1353", "target": "views_workshopviewset", "relation": "rationale_for", "confidence": "EXTRACTED", "source_file": "apps\\learning\\views.py", "source_location": "L1353", "weight": 1.0}]}